flask_grpc_bridge/__init__.py
flask_grpc_bridge/bridge.py
flask_grpc_bridge/py.typed
flask_grpc_bridge-0.0.2.dist-info/LICENSE
flask_grpc_bridge-0.0.2.dist-info/METADATA
flask_grpc_bridge-0.0.2.dist-info/WHEEL
flask_grpc_bridge-0.0.2.dist-info/top_level.txt
flask_grpc_bridge-0.0.2.dist-info/RECORD
