Metadata-Version: 2.1
Name: flask-grpc-bridge
Version: 0.0.2
Summary: Bridge between Flask and gRPC definitions.
Home-page: https://github.com/chriselion/flask-grpc-bridge
Author: Chris Elion
Author-email: celion@alumni.caltech.edu
License: MIT
Classifier: License :: OSI Approved :: MIT License
Classifier: Programming Language :: Python :: 3
Classifier: Programming Language :: Python :: 3 :: Only
Classifier: Programming Language :: Python :: Implementation :: CPython
Classifier: Programming Language :: Python :: Implementation :: PyPy
Requires-Python: >=3.8
License-File: LICENSE
Requires-Dist: flask
Requires-Dist: grpcio
Requires-Dist: typing-extensions
